{
  "generated_at": "2026-06-12T16:21:53.098152",
  "picks": [
    {
      "id": "2026-06-12-Was-Sea-rl",
      "date": "2026-06-12",
      "type": "runline",
      "matchup": "Seattle Mariners @ Washington Nationals",
      "home": "Washington Nationals",
      "away": "Seattle Mariners",
      "pick": "Seattle Mariners +1.5",
      "odds": "-110",
      "confidence": 73,
      "home_sp": "Zack Littell",
      "away_sp": "Bryce Miller",
      "edge": "+1.2 runs",
      "notes": "Model margin: -2.7 runs. DK spread: +1.5.",
      "result": "PENDING",
      "dk_total": 9.5,
      "dk_spread": 1.5
    },
    {
      "id": "2026-06-12-Bal-San-ml",
      "date": "2026-06-12",
      "type": "moneyline",
      "matchup": "San Diego Padres @ Baltimore Orioles",
      "home": "Baltimore Orioles",
      "away": "San Diego Padres",
      "pick": "San Diego Padres",
      "odds": "+108",
      "confidence": 59,
      "home_sp": "Shane Baz",
      "away_sp": "Griffin Canning",
      "edge": "+34 pts vs fair +142",
      "notes": "Model win prob: 41.3%. Fair line: +142. DK: +108.",
      "result": "PENDING",
      "dk_total": 9.5,
      "dk_spread": -1.5
    },
    {
      "id": "2026-06-12-Bal-San-rl",
      "date": "2026-06-12",
      "type": "runline",
      "matchup": "San Diego Padres @ Baltimore Orioles",
      "home": "Baltimore Orioles",
      "away": "San Diego Padres",
      "pick": "Baltimore Orioles -1.5",
      "odds": "-110",
      "confidence": 50,
      "home_sp": "Shane Baz",
      "away_sp": "Griffin Canning",
      "edge": "-0.0 runs",
      "notes": "Model margin: +1.5 runs. DK spread: -1.5.",
      "result": "PENDING",
      "dk_total": 9.5,
      "dk_spread": -1.5
    },
    {
      "id": "2026-06-12-Bos-Tex-ml",
      "date": "2026-06-12",
      "type": "moneyline",
      "matchup": "Texas Rangers @ Boston Red Sox",
      "home": "Boston Red Sox",
      "away": "Texas Rangers",
      "pick": "Texas Rangers",
      "odds": "+116",
      "confidence": 55,
      "home_sp": "Sonny Gray",
      "away_sp": "Jack Leiter",
      "edge": "+8 pts vs fair +124",
      "notes": "Model win prob: 44.7%. Fair line: +124. DK: +116.",
      "result": "PENDING",
      "dk_total": 8.5,
      "dk_spread": -1.5
    },
    {
      "id": "2026-06-12-Bos-Tex-rl",
      "date": "2026-06-12",
      "type": "runline",
      "matchup": "Texas Rangers @ Boston Red Sox",
      "home": "Boston Red Sox",
      "away": "Texas Rangers",
      "pick": "Boston Red Sox -1.5",
      "odds": "-110",
      "confidence": 79,
      "home_sp": "Sonny Gray",
      "away_sp": "Jack Leiter",
      "edge": "-1.5 runs",
      "notes": "Model margin: +0.0 runs. DK spread: -1.5.",
      "result": "PENDING",
      "dk_total": 8.5,
      "dk_spread": -1.5
    },
    {
      "id": "2026-06-12-Cle-Det-rl",
      "date": "2026-06-12",
      "type": "runline",
      "matchup": "Detroit Tigers @ Cleveland Guardians",
      "home": "Cleveland Guardians",
      "away": "Detroit Tigers",
      "pick": "Cleveland Guardians -1.5",
      "odds": "-110",
      "confidence": 63,
      "home_sp": "Tanner Bibee",
      "away_sp": "Jack Flaherty",
      "edge": "-0.7 runs",
      "notes": "Model margin: +0.8 runs. DK spread: -1.5.",
      "result": "PENDING",
      "dk_total": 8.5,
      "dk_spread": -1.5
    },
    {
      "id": "2026-06-12-New-Atl-ml",
      "date": "2026-06-12",
      "type": "moneyline",
      "matchup": "Atlanta Braves @ New York Mets",
      "home": "New York Mets",
      "away": "Atlanta Braves",
      "pick": "Atlanta Braves",
      "odds": "+105",
      "confidence": 62,
      "home_sp": "Nolan McLean",
      "away_sp": "Spencer Strider",
      "edge": "+59 pts vs fair +164",
      "notes": "Model win prob: 37.8%. Fair line: +164. DK: +105.",
      "result": "PENDING",
      "dk_total": 8.0,
      "dk_spread": -1.5
    },
    {
      "id": "2026-06-12-Cin-Ari-ml",
      "date": "2026-06-12",
      "type": "moneyline",
      "matchup": "Arizona Diamondbacks @ Cincinnati Reds",
      "home": "Cincinnati Reds",
      "away": "Arizona Diamondbacks",
      "pick": "Arizona Diamondbacks",
      "odds": "-105",
      "confidence": 62,
      "home_sp": "Nick Lodolo",
      "away_sp": "Eduardo Rodriguez",
      "edge": "+268 pts vs fair +163",
      "notes": "Model win prob: 38.0%. Fair line: +163. DK: -105.",
      "result": "PENDING",
      "dk_total": 9.5,
      "dk_spread": 1.5
    },
    {
      "id": "2026-06-12-Tor-New-ml",
      "date": "2026-06-12",
      "type": "moneyline",
      "matchup": "New York Yankees @ Toronto Blue Jays",
      "home": "Toronto Blue Jays",
      "away": "New York Yankees",
      "pick": "New York Yankees",
      "odds": "-105",
      "confidence": 63,
      "home_sp": "Trey Yesavage",
      "away_sp": "Ryan Weathers",
      "edge": "+275 pts vs fair +170",
      "notes": "Model win prob: 37.1%. Fair line: +170. DK: -105.",
      "result": "PENDING",
      "dk_total": 8.0,
      "dk_spread": 1.5
    },
    {
      "id": "2026-06-12-Tor-New-rl",
      "date": "2026-06-12",
      "type": "runline",
      "matchup": "New York Yankees @ Toronto Blue Jays",
      "home": "Toronto Blue Jays",
      "away": "New York Yankees",
      "pick": "New York Yankees +1.5",
      "odds": "-110",
      "confidence": 55,
      "home_sp": "Trey Yesavage",
      "away_sp": "Ryan Weathers",
      "edge": "-0.3 runs",
      "notes": "Model margin: -1.2 runs. DK spread: +1.5.",
      "result": "PENDING",
      "dk_total": 8.0,
      "dk_spread": 1.5
    },
    {
      "id": "2026-06-12-Chi-Los-ml",
      "date": "2026-06-12",
      "type": "moneyline",
      "matchup": "Los Angeles Dodgers @ Chicago White Sox",
      "home": "Chicago White Sox",
      "away": "Los Angeles Dodgers",
      "pick": "Los Angeles Dodgers",
      "odds": "-171",
      "confidence": 71,
      "home_sp": "Anthony Kay",
      "away_sp": "Roki Sasaki",
      "edge": "+417 pts vs fair +246",
      "notes": "Model win prob: 28.9%. Fair line: +246. DK: -171.",
      "result": "PENDING",
      "dk_total": 9.0,
      "dk_spread": 1.5
    },
    {
      "id": "2026-06-12-Chi-Los-rl",
      "date": "2026-06-12",
      "type": "runline",
      "matchup": "Los Angeles Dodgers @ Chicago White Sox",
      "home": "Chicago White Sox",
      "away": "Los Angeles Dodgers",
      "pick": "Los Angeles Dodgers +1.5",
      "odds": "-110",
      "confidence": 73,
      "home_sp": "Anthony Kay",
      "away_sp": "Roki Sasaki",
      "edge": "+1.2 runs",
      "notes": "Model margin: -2.7 runs. DK spread: +1.5.",
      "result": "PENDING",
      "dk_total": 9.0,
      "dk_spread": 1.5
    },
    {
      "id": "2026-06-12-Mil-Phi-rl",
      "date": "2026-06-12",
      "type": "runline",
      "matchup": "Philadelphia Phillies @ Milwaukee Brewers",
      "home": "Milwaukee Brewers",
      "away": "Philadelphia Phillies",
      "pick": "Milwaukee Brewers -1.5",
      "odds": "-110",
      "confidence": 66,
      "home_sp": "Jacob Misiorowski",
      "away_sp": "Andrew Painter",
      "edge": "-0.8 runs",
      "notes": "Model margin: +0.7 runs. DK spread: -1.5.",
      "result": "PENDING",
      "dk_total": 7.5,
      "dk_spread": -1.5
    },
    {
      "id": "2026-06-12-Kan-Hou-ml",
      "date": "2026-06-12",
      "type": "moneyline",
      "matchup": "Houston Astros @ Kansas City Royals",
      "home": "Kansas City Royals",
      "away": "Houston Astros",
      "pick": "Kansas City Royals",
      "odds": "-105",
      "confidence": 62,
      "home_sp": "Luinder Avila",
      "away_sp": "Tatsuya Imai",
      "edge": "+60 pts vs fair -165",
      "notes": "Model win prob: 62.3%. Fair line: -165. DK: -105.",
      "result": "PENDING",
      "dk_total": 9.5,
      "dk_spread": 1.5
    },
    {
      "id": "2026-06-12-Min-St.-ml",
      "date": "2026-06-12",
      "type": "moneyline",
      "matchup": "St. Louis Cardinals @ Minnesota Twins",
      "home": "Minnesota Twins",
      "away": "St. Louis Cardinals",
      "pick": "St. Louis Cardinals",
      "odds": "+114",
      "confidence": 68,
      "home_sp": "Joe Ryan",
      "away_sp": "Kyle Leahy",
      "edge": "+96 pts vs fair +210",
      "notes": "Model win prob: 32.2%. Fair line: +210. DK: +114.",
      "result": "PENDING",
      "dk_total": 9.0,
      "dk_spread": -1.5
    },
    {
      "id": "2026-06-12-Los-Tam-ml",
      "date": "2026-06-12",
      "type": "moneyline",
      "matchup": "Tampa Bay Rays @ Los Angeles Angels",
      "home": "Los Angeles Angels",
      "away": "Tampa Bay Rays",
      "pick": "Tampa Bay Rays",
      "odds": "-171",
      "confidence": 66,
      "home_sp": "Sam Aldegheri",
      "away_sp": "Shane McClanahan",
      "edge": "+364 pts vs fair +193",
      "notes": "Model win prob: 34.2%. Fair line: +193. DK: -171.",
      "result": "PENDING",
      "dk_total": 9.0,
      "dk_spread": 1.5
    },
    {
      "id": "2026-06-12-Los-Tam-total",
      "date": "2026-06-12",
      "type": "total",
      "matchup": "Tampa Bay Rays @ Los Angeles Angels",
      "home": "Los Angeles Angels",
      "away": "Tampa Bay Rays",
      "pick": "OVER 9.0",
      "odds": "-110",
      "confidence": 86,
      "home_sp": "Sam Aldegheri",
      "away_sp": "Shane McClanahan",
      "edge": "+1.8 runs",
      "notes": "Model predicts 10.8 runs. DK line: 9.0.",
      "result": "PENDING",
      "dk_total": 9.0,
      "dk_spread": 1.5
    },
    {
      "id": "2026-06-12-Ath-Col-total",
      "date": "2026-06-12",
      "type": "total",
      "matchup": "Colorado Rockies @ Athletics",
      "home": "Athletics",
      "away": "Colorado Rockies",
      "pick": "UNDER 14.0",
      "odds": "-110",
      "confidence": 92,
      "home_sp": "Gage Jump",
      "away_sp": "TBD",
      "edge": "-3.0 runs",
      "notes": "Model predicts 11.0 runs. DK line: 14.0.",
      "result": "PENDING",
      "dk_total": 14.0,
      "dk_spread": -1.5
    },
    {
      "id": "2026-06-12-Ath-Col-rl",
      "date": "2026-06-12",
      "type": "runline",
      "matchup": "Colorado Rockies @ Athletics",
      "home": "Athletics",
      "away": "Colorado Rockies",
      "pick": "Athletics -1.5",
      "odds": "-110",
      "confidence": 55,
      "home_sp": "Gage Jump",
      "away_sp": "TBD",
      "edge": "-0.3 runs",
      "notes": "Model margin: +1.2 runs. DK spread: -1.5.",
      "result": "PENDING",
      "dk_total": 14.0,
      "dk_spread": -1.5
    },
    {
      "id": "2026-06-12-San-Chi-ml",
      "date": "2026-06-12",
      "type": "moneyline",
      "matchup": "Chicago Cubs @ San Francisco Giants",
      "home": "San Francisco Giants",
      "away": "Chicago Cubs",
      "pick": "Chicago Cubs",
      "odds": "+104",
      "confidence": 62,
      "home_sp": "Landen Roupp",
      "away_sp": "Javier Assad",
      "edge": "+61 pts vs fair +165",
      "notes": "Model win prob: 37.7%. Fair line: +165. DK: +104.",
      "result": "PENDING",
      "dk_total": 8.5,
      "dk_spread": 1.5
    }
  ],
  "record": {
    "moneyline": {
      "wins": 47,
      "losses": 49
    },
    "total": {
      "wins": 29,
      "losses": 23
    },
    "runline": {
      "wins": 44,
      "losses": 79
    }
  }
}